flag_bearer/__init__.py
flag_bearer/actions.py
flag_bearer/cli.py
flag_bearer/config.py
flag_bearer/default.ini
flag_bearer/remote.py
flag_bearer/utils.py
flag_bearer-0.2.dist-info/DESCRIPTION.rst
flag_bearer-0.2.dist-info/METADATA
flag_bearer-0.2.dist-info/RECORD
flag_bearer-0.2.dist-info/WHEEL
flag_bearer-0.2.dist-info/entry_points.txt
flag_bearer-0.2.dist-info/metadata.json
flag_bearer-0.2.dist-info/top_level.txt
tests/__init__.py
tests/test_config.py
tests/test_utils.py
