Metadata-Version: 2.0
Name: flag-bearer
Version: 0.2
Summary: CDC IScorE Flag Utility
Home-page: http://github.com/ISEAGE-ISU/flag-bearer
Author: ISEAGE
Author-email: iseage@iastate.edu
License: MIT
Platform: UNKNOWN
Classifier: Development Status :: 4 - Beta
Classifier: Programming Language :: Python :: 2
Classifier: Programming Language :: Python :: 2.7
Classifier: Programming Language :: Python :: 3
Classifier: Programming Language :: Python :: 3.4
Classifier: Programming Language :: Python :: 3.5
Classifier: Programming Language :: Python :: 3.6
Classifier: Topic :: Internet :: WWW/HTTP
Classifier: License :: OSI Approved :: MIT License
Requires-Dist: requests
Requires-Dist: six
Provides-Extra: remote
Requires-Dist: paramiko; extra == 'remote'
Provides-Extra: tests
Requires-Dist: vcrpy; extra == 'tests'
Requires-Dist: pytest; extra == 'tests'
Requires-Dist: tox; extra == 'tests'
